pdbio/__init__.py
pdbio/bamwriter.py
pdbio/beddataframe.py
pdbio/biodataframe.py
pdbio/cli.py
pdbio/identifier.py
pdbio/samcigar.py
pdbio/samdataframe.py
pdbio/vcfdataframe.py
pdbio-0.4.2.dist-info/LICENSE
pdbio-0.4.2.dist-info/METADATA
pdbio-0.4.2.dist-info/WHEEL
pdbio-0.4.2.dist-info/entry_points.txt
pdbio-0.4.2.dist-info/top_level.txt
pdbio-0.4.2.dist-info/RECORD
