Metadata-Version: 2.1
Name: pdbio
Version: 0.4.2
Summary: Pandas-based Data Handler for VCF, BED, and SAM Files
Home-page: https://github.com/dceoy/pdbio
Author: Daichi Narushima
Author-email: dnarsil+github@gmail.com
License: UNKNOWN
Platform: UNKNOWN
Classifier: Development Status :: 4 - Beta
Classifier: Environment :: Console
Classifier: Environment :: Plugins
Classifier: License :: OSI Approved :: MIT License
Classifier: Operating System :: POSIX :: Linux
Classifier: Operating System :: MacOS
Classifier: Programming Language :: Python :: 3
Classifier: Topic :: Scientific/Engineering :: Bio-Informatics
Requires-Python: >=3.6
Requires-Dist: docopt
Requires-Dist: pandas
